_version.py
condition_report_service.py
t2d2_sdk.py
test.py
t2d2_sdk-2.4.9.dist-info/licenses/LICENSE
t2d2_sdk-2.4.9.dist-info/METADATA
t2d2_sdk-2.4.9.dist-info/WHEEL
t2d2_sdk-2.4.9.dist-info/top_level.txt
t2d2_sdk-2.4.9.dist-info/RECORD
