Metadata-Version: 2.4
Name: t2d2-sdk
Version: 2.4.9
Summary: T2D2 SDK
Author-email: Badri Hiriyur <badri@t2d2.ai>
Project-URL: Homepage, https://t2d2.ai
Project-URL: Issues, https://github.com/t2d2-ai/t2d2-sdk/issues
Classifier: Programming Language :: Python :: 3
Classifier: License :: OSI Approved :: BSD License
Classifier: Operating System :: OS Independent
Requires-Python: >=3.8
License-File: LICENSE
Requires-Dist: boto3
Requires-Dist: requests
Requires-Dist: sentry_sdk
Dynamic: license-file
